{
  "version": "1.0",
  "exportedAt": 1706140900000,
  "groups": [
    {
      "id": "g1",
      "name": "Artigos",
      "createdAt": 1706140800000
    },
    {
      "id": "g2",
      "name": "Pronomes e Determinantes",
      "createdAt": 1706140800000
    },
    {
      "id": "g3",
      "name": "Preposições Essenciais",
      "createdAt": 1706140800000
    },
    {
      "id": "g4",
      "name": "Conectores",
      "createdAt": 1706140800000
    },
    {
      "id": "g5",
      "name": "Auxiliares",
      "createdAt": 1706140800000
    }
  ],
  "cards": [
    {
      "id": "p2-card-1",
      "groupId": "g1",
      "portuguesePhrase": "Eu preciso de uma caneta.",
      "englishPhrase": "I need a pen.",
      "direction": "en-pt",
      "level": 1,
      "lastReviewed": null,
      "nextReview": 1706140900000,
      "errorCount": 0,
      "tips": "'A' antes de consoante, qualquer caneta serve.",
      "createdAt": 1706140900000
    },
    {
      "id": "p2-card-2",
      "groupId": "g1",
      "portuguesePhrase": "Ele é um médico.",
      "englishPhrase": "He is a doctor.",
      "direction": "en-pt",
      "level": 1,
      "lastReviewed": null,
      "nextReview": 1706140900000,
      "errorCount": 0,
      "tips": "Profissões usam artigo indefinido em inglês.",
      "createdAt": 1706140900000
    },
    {
      "id": "p2-card-3",
      "groupId": "g1",
      "portuguesePhrase": "Ela comeu uma maçã.",
      "englishPhrase": "She ate an apple.",
      "direction": "en-pt",
      "level": 1,
      "lastReviewed": null,
      "nextReview": 1706140900000,
      "errorCount": 0,
      "tips": "'An' antes de som de vogal (apple começa com /æ/).",
      "createdAt": 1706140900000
    },
    {
      "id": "p2-card-4",
      "groupId": "g1",
      "portuguesePhrase": "A lua está brilhante.",
      "englishPhrase": "The moon is bright.",
      "direction": "en-pt",
      "level": 1,
      "lastReviewed": null,
      "nextReview": 1706140900000,
      "errorCount": 0,
      "tips": "Astros únicos usam 'the'.",
      "createdAt": 1706140900000
    },
    {
      "id": "p2-card-5",
      "groupId": "g1",
      "portuguesePhrase": "Água é essencial.",
      "englishPhrase": "Water is essential.",
      "direction": "en-pt",
      "level": 1,
      "lastReviewed": null,
      "nextReview": 1706140900000,
      "errorCount": 0,
      "tips": "Substantivos incontáveis genéricos não usam artigo.",
      "createdAt": 1706140900000
    },
    {
      "id": "p2-card-6",
      "groupId": "g1",
      "portuguesePhrase": "Gatos são independentes.",
      "englishPhrase": "Cats are independent.",
      "direction": "en-pt",
      "level": 1,
      "lastReviewed": null,
      "nextReview": 1706140900000,
      "errorCount": 0,
      "tips": "Generalizações no plural não usam artigo.",
      "createdAt": 1706140900000
    },
    {
      "id": "p2-card-7",
      "groupId": "g1",
      "portuguesePhrase": "Esta camisa é cara.",
      "englishPhrase": "This shirt is expensive.",
      "direction": "en-pt",
      "level": 1,
      "lastReviewed": null,
      "nextReview": 1706140900000,
      "errorCount": 0,
      "tips": "'This' para objeto próximo no singular.",
      "createdAt": 1706140900000
    },
    {
      "id": "p2-card-8",
      "groupId": "g1",
      "portuguesePhrase": "Aquele prédio é alto.",
      "englishPhrase": "That building is tall.",
      "direction": "en-pt",
      "level": 1,
      "lastReviewed": null,
      "nextReview": 1706140900000,
      "errorCount": 0,
      "tips": "'That' para objeto distante no singular.",
      "createdAt": 1706140900000
    },
    {
      "id": "p2-card-9",
      "groupId": "g1",
      "portuguesePhrase": "Sua casa é bonita.",
      "englishPhrase": "Your house is beautiful.",
      "direction": "en-pt",
      "level": 1,
      "lastReviewed": null,
      "nextReview": 1706140900000,
      "errorCount": 0,
      "tips": "'Your' substitui o artigo definido.",
      "createdAt": 1706140900000
    },
    {
      "id": "p2-card-10",
      "groupId": "g1",
      "portuguesePhrase": "Ele é um homem honesto.",
      "englishPhrase": "He is an honest man.",
      "direction": "en-pt",
      "level": 1,
      "lastReviewed": null,
      "nextReview": 1706140900000,
      "errorCount": 0,
      "tips": "'An' porque o 'h' de 'honest' é mudo.",
      "createdAt": 1706140900000
    },
    {
      "id": "p2-card-11",
      "groupId": "g2",
      "portuguesePhrase": "Nós somos estudantes.",
      "englishPhrase": "We are students.",
      "direction": "en-pt",
      "level": 1,
      "lastReviewed": null,
      "nextReview": 1706140900000,
      "errorCount": 0,
      "tips": "'We' inclui o falante no grupo.",
      "createdAt": 1706140900000
    },
    {
      "id": "p2-card-12",
      "groupId": "g2",
      "portuguesePhrase": "Você pode me ajudar?",
      "englishPhrase": "Can you help me?",
      "direction": "en-pt",
      "level": 1,
      "lastReviewed": null,
      "nextReview": 1706140900000,
      "errorCount": 0,
      "tips": "'You' serve para singular e plural.",
      "createdAt": 1706140900000
    },
    {
      "id": "p2-card-13",
      "groupId": "g2",
      "portuguesePhrase": "Ele me deu um presente.",
      "englishPhrase": "He gave me a gift.",
      "direction": "en-pt",
      "level": 1,
      "lastReviewed": null,
      "nextReview": 1706140900000,
      "errorCount": 0,
      "tips": "'Me' é objeto indireto aqui.",
      "createdAt": 1706140900000
    },
    {
      "id": "p2-card-14",
      "groupId": "g2",
      "portuguesePhrase": "Eu vi ela ontem.",
      "englishPhrase": "I saw her yesterday.",
      "direction": "en-pt",
      "level": 1,
      "lastReviewed": null,
      "nextReview": 1706140900000,
      "errorCount": 0,
      "tips": "'Her' como objeto direto.",
      "createdAt": 1706140900000
    },
    {
      "id": "p2-card-15",
      "groupId": "g2",
      "portuguesePhrase": "O carro é dele.",
      "englishPhrase": "The car is his.",
      "direction": "en-pt",
      "level": 1,
      "lastReviewed": null,
      "nextReview": 1706140900000,
      "errorCount": 0,
      "tips": "'His' pode ser adjetivo ou pronome.",
      "createdAt": 1706140900000
    },
    {
      "id": "p2-card-16",
      "groupId": "g2",
      "portuguesePhrase": "Esse problema é nosso.",
      "englishPhrase": "This problem is ours.",
      "direction": "en-pt",
      "level": 1,
      "lastReviewed": null,
      "nextReview": 1706140900000,
      "errorCount": 0,
      "tips": "'Ours' substitui 'our + substantivo'.",
      "createdAt": 1706140900000
    },
    {
      "id": "p2-card-17",
      "groupId": "g2",
      "portuguesePhrase": "Cada aluno tem um livro.",
      "englishPhrase": "Each student has a book.",
      "direction": "en-pt",
      "level": 1,
      "lastReviewed": null,
      "nextReview": 1706140900000,
      "errorCount": 0,
      "tips": "'Each' enfatiza indivíduos separadamente.",
      "createdAt": 1706140900000
    },
    {
      "id": "p2-card-18",
      "groupId": "g2",
      "portuguesePhrase": "Todo mundo sabe disso.",
      "englishPhrase": "Everyone knows that.",
      "direction": "en-pt",
      "level": 1,
      "lastReviewed": null,
      "nextReview": 1706140900000,
      "errorCount": 0,
      "tips": "'Everyone' usa verbo no singular.",
      "createdAt": 1706140900000
    },
    {
      "id": "p2-card-19",
      "groupId": "g2",
      "portuguesePhrase": "Alguém ligou para você.",
      "englishPhrase": "Someone called you.",
      "direction": "en-pt",
      "level": 1,
      "lastReviewed": null,
      "nextReview": 1706140900000,
      "errorCount": 0,
      "tips": "'Someone' para pessoa indefinida.",
      "createdAt": 1706140900000
    },
    {
      "id": "p2-card-20",
      "groupId": "g2",
      "portuguesePhrase": "Ninguém veio à festa.",
      "englishPhrase": "Nobody came to the party.",
      "direction": "en-pt",
      "level": 1,
      "lastReviewed": null,
      "nextReview": 1706140900000,
      "errorCount": 0,
      "tips": "'Nobody' já é negativo, não use 'not'.",
      "createdAt": 1706140900000
    },
    {
      "id": "p2-card-21",
      "groupId": "g3",
      "portuguesePhrase": "Ela chegou às 9 horas.",
      "englishPhrase": "She arrived at 9 o'clock.",
      "direction": "en-pt",
      "level": 1,
      "lastReviewed": null,
      "nextReview": 1706140900000,
      "errorCount": 0,
      "tips": "'At' para horas específicas.",
      "createdAt": 1706140900000
    },
    {
      "id": "p2-card-22",
      "groupId": "g3",
      "portuguesePhrase": "Eu nasci em maio.",
      "englishPhrase": "I was born in May.",
      "direction": "en-pt",
      "level": 1,
      "lastReviewed": null,
      "nextReview": 1706140900000,
      "errorCount": 0,
      "tips": "'In' para meses e anos.",
      "createdAt": 1706140900000
    },
    {
      "id": "p2-card-23",
      "groupId": "g3",
      "portuguesePhrase": "Ele trabalha aos sábados.",
      "englishPhrase": "He works on Saturdays.",
      "direction": "en-pt",
      "level": 1,
      "lastReviewed": null,
      "nextReview": 1706140900000,
      "errorCount": 0,
      "tips": "'On' para dias da semana.",
      "createdAt": 1706140900000
    },
    {
      "id": "p2-card-24",
      "groupId": "g3",
      "portuguesePhrase": "O gato está debaixo da cama.",
      "englishPhrase": "The cat is under the bed.",
      "direction": "en-pt",
      "level": 1,
      "lastReviewed": null,
      "nextReview": 1706140900000,
      "errorCount": 0,
      "tips": "'Under' indica posição abaixo.",
      "createdAt": 1706140900000
    },
    {
      "id": "p2-card-25",
      "groupId": "g3",
      "portuguesePhrase": "Há uma lâmpada acima da mesa.",
      "englishPhrase": "There is a lamp above the table.",
      "direction": "en-pt",
      "level": 1,
      "lastReviewed": null,
      "nextReview": 1706140900000,
      "errorCount": 0,
      "tips": "'Above' indica posição acima sem contato.",
      "createdAt": 1706140900000
    },
    {
      "id": "p2-card-26",
      "groupId": "g3",
      "portuguesePhrase": "Ela está atrás de mim.",
      "englishPhrase": "She is behind me.",
      "direction": "en-pt",
      "level": 1,
      "lastReviewed": null,
      "nextReview": 1706140900000,
      "errorCount": 0,
      "tips": "'Behind' indica posição atrás.",
      "createdAt": 1706140900000
    },
    {
      "id": "p2-card-27",
      "groupId": "g3",
      "portuguesePhrase": "A farmácia fica perto daqui.",
      "englishPhrase": "The pharmacy is near here.",
      "direction": "en-pt",
      "level": 1,
      "lastReviewed": null,
      "nextReview": 1706140900000,
      "errorCount": 0,
      "tips": "'Near' indica proximidade.",
      "createdAt": 1706140900000
    },
    {
      "id": "p2-card-28",
      "groupId": "g3",
      "portuguesePhrase": "Ele passou pela porta.",
      "englishPhrase": "He walked through the door.",
      "direction": "en-pt",
      "level": 1,
      "lastReviewed": null,
      "nextReview": 1706140900000,
      "errorCount": 0,
      "tips": "'Through' indica atravessar algo.",
      "createdAt": 1706140900000
    },
    {
      "id": "p2-card-29",
      "groupId": "g3",
      "portuguesePhrase": "Estou esperando por você.",
      "englishPhrase": "I am waiting for you.",
      "direction": "en-pt",
      "level": 1,
      "lastReviewed": null,
      "nextReview": 1706140900000,
      "errorCount": 0,
      "tips": "'Wait for' é a combinação correta.",
      "createdAt": 1706140900000
    },
    {
      "id": "p2-card-30",
      "groupId": "g3",
      "portuguesePhrase": "Ela concordou comigo.",
      "englishPhrase": "She agreed with me.",
      "direction": "en-pt",
      "level": 1,
      "lastReviewed": null,
      "nextReview": 1706140900000,
      "errorCount": 0,
      "tips": "'Agree with' para concordar com pessoa.",
      "createdAt": 1706140900000
    },
    {
      "id": "p2-card-31",
      "groupId": "g4",
      "portuguesePhrase": "Eu estudei, portanto passei.",
      "englishPhrase": "I studied, therefore I passed.",
      "direction": "en-pt",
      "level": 1,
      "lastReviewed": null,
      "nextReview": 1706140900000,
      "errorCount": 0,
      "tips": "'Therefore' é mais formal que 'so'.",
      "createdAt": 1706140900000
    },
    {
      "id": "p2-card-32",
      "groupId": "g4",
      "portuguesePhrase": "Ele é rico, porém infeliz.",
      "englishPhrase": "He is rich, however unhappy.",
      "direction": "en-pt",
      "level": 1,
      "lastReviewed": null,
      "nextReview": 1706140900000,
      "errorCount": 0,
      "tips": "'However' é mais formal que 'but'.",
      "createdAt": 1706140900000
    },
    {
      "id": "p2-card-33",
      "groupId": "g4",
      "portuguesePhrase": "Eu gosto tanto de chá quanto de café.",
      "englishPhrase": "I like both tea and coffee.",
      "direction": "en-pt",
      "level": 1,
      "lastReviewed": null,
      "nextReview": 1706140900000,
      "errorCount": 0,
      "tips": "'Both...and' para duas coisas igualmente.",
      "createdAt": 1706140900000
    },
    {
      "id": "p2-card-34",
      "groupId": "g4",
      "portuguesePhrase": "Ou você vai ou eu vou.",
      "englishPhrase": "Either you go or I go.",
      "direction": "en-pt",
      "level": 1,
      "lastReviewed": null,
      "nextReview": 1706140900000,
      "errorCount": 0,
      "tips": "'Either...or' para uma escolha entre duas.",
      "createdAt": 1706140900000
    },
    {
      "id": "p2-card-35",
      "groupId": "g4",
      "portuguesePhrase": "Nem eu nem ele sabemos.",
      "englishPhrase": "Neither I nor he knows.",
      "direction": "en-pt",
      "level": 1,
      "lastReviewed": null,
      "nextReview": 1706140900000,
      "errorCount": 0,
      "tips": "'Neither...nor' para negar duas coisas.",
      "createdAt": 1706140900000
    },
    {
      "id": "p2-card-36",
      "groupId": "g4",
      "portuguesePhrase": "Embora estivesse cansado, continuei.",
      "englishPhrase": "Although I was tired, I continued.",
      "direction": "en-pt",
      "level": 1,
      "lastReviewed": null,
      "nextReview": 1706140900000,
      "errorCount": 0,
      "tips": "'Although' introduz concessão.",
      "createdAt": 1706140900000
    },
    {
      "id": "p2-card-37",
      "groupId": "g4",
      "portuguesePhrase": "Desde que você prometa.",
      "englishPhrase": "As long as you promise.",
      "direction": "en-pt",
      "level": 1,
      "lastReviewed": null,
      "nextReview": 1706140900000,
      "errorCount": 0,
      "tips": "'As long as' indica condição.",
      "createdAt": 1706140900000
    },
    {
      "id": "p2-card-38",
      "groupId": "g4",
      "portuguesePhrase": "A menos que chova, iremos.",
      "englishPhrase": "Unless it rains, we will go.",
      "direction": "en-pt",
      "level": 1,
      "lastReviewed": null,
      "nextReview": 1706140900000,
      "errorCount": 0,
      "tips": "'Unless' = 'if not'.",
      "createdAt": 1706140900000
    },
    {
      "id": "p2-card-39",
      "groupId": "g4",
      "portuguesePhrase": "Ela ficou ainda que todos saíram.",
      "englishPhrase": "She stayed even though everyone left.",
      "direction": "en-pt",
      "level": 1,
      "lastReviewed": null,
      "nextReview": 1706140900000,
      "errorCount": 0,
      "tips": "'Even though' enfatiza contraste.",
      "createdAt": 1706140900000
    },
    {
      "id": "p2-card-40",
      "groupId": "g4",
      "portuguesePhrase": "Assim que chegar, me avise.",
      "englishPhrase": "As soon as you arrive, let me know.",
      "direction": "en-pt",
      "level": 1,
      "lastReviewed": null,
      "nextReview": 1706140900000,
      "errorCount": 0,
      "tips": "'As soon as' indica imediatamente após.",
      "createdAt": 1706140900000
    },
    {
      "id": "p2-card-41",
      "groupId": "g5",
      "portuguesePhrase": "Eu estava dormindo.",
      "englishPhrase": "I was sleeping.",
      "direction": "en-pt",
      "level": 1,
      "lastReviewed": null,
      "nextReview": 1706140900000,
      "errorCount": 0,
      "tips": "'Was' + ing = passado contínuo.",
      "createdAt": 1706140900000
    },
    {
      "id": "p2-card-42",
      "groupId": "g5",
      "portuguesePhrase": "Eles estavam estudando.",
      "englishPhrase": "They were studying.",
      "direction": "en-pt",
      "level": 1,
      "lastReviewed": null,
      "nextReview": 1706140900000,
      "errorCount": 0,
      "tips": "'Were' para plural no passado contínuo.",
      "createdAt": 1706140900000
    },
    {
      "id": "p2-card-43",
      "groupId": "g5",
      "portuguesePhrase": "Você poderia me ajudar?",
      "englishPhrase": "Could you help me?",
      "direction": "en-pt",
      "level": 1,
      "lastReviewed": null,
      "nextReview": 1706140900000,
      "errorCount": 0,
      "tips": "'Could' é mais educado que 'can'.",
      "createdAt": 1706140900000
    },
    {
      "id": "p2-card-44",
      "groupId": "g5",
      "portuguesePhrase": "Você deveria descansar.",
      "englishPhrase": "You should rest.",
      "direction": "en-pt",
      "level": 1,
      "lastReviewed": null,
      "nextReview": 1706140900000,
      "errorCount": 0,
      "tips": "'Should' para conselho.",
      "createdAt": 1706140900000
    },
    {
      "id": "p2-card-45",
      "groupId": "g5",
      "portuguesePhrase": "Eu posso estar errado.",
      "englishPhrase": "I might be wrong.",
      "direction": "en-pt",
      "level": 1,
      "lastReviewed": null,
      "nextReview": 1706140900000,
      "errorCount": 0,
      "tips": "'Might' indica possibilidade menor que 'may'.",
      "createdAt": 1706140900000
    },
    {
      "id": "p2-card-46",
      "groupId": "g5",
      "portuguesePhrase": "Você deve usar cinto.",
      "englishPhrase": "You must wear a seatbelt.",
      "direction": "en-pt",
      "level": 1,
      "lastReviewed": null,
      "nextReview": 1706140900000,
      "errorCount": 0,
      "tips": "'Must' indica obrigação forte.",
      "createdAt": 1706140900000
    },
    {
      "id": "p2-card-47",
      "groupId": "g5",
      "portuguesePhrase": "Eu terei que ir.",
      "englishPhrase": "I will have to go.",
      "direction": "en-pt",
      "level": 1,
      "lastReviewed": null,
      "nextReview": 1706140900000,
      "errorCount": 0,
      "tips": "'Will have to' = obrigação futura.",
      "createdAt": 1706140900000
    },
    {
      "id": "p2-card-48",
      "groupId": "g5",
      "portuguesePhrase": "Ela tinha terminado antes.",
      "englishPhrase": "She had finished before.",
      "direction": "en-pt",
      "level": 1,
      "lastReviewed": null,
      "nextReview": 1706140900000,
      "errorCount": 0,
      "tips": "'Had' + particípio = passado perfeito.",
      "createdAt": 1706140900000
    },
    {
      "id": "p2-card-49",
      "groupId": "g5",
      "portuguesePhrase": "Isso seria ótimo.",
      "englishPhrase": "That would be great.",
      "direction": "en-pt",
      "level": 1,
      "lastReviewed": null,
      "nextReview": 1706140900000,
      "errorCount": 0,
      "tips": "'Would' para situações hipotéticas.",
      "createdAt": 1706140900000
    },
    {
      "id": "p2-card-50",
      "groupId": "g5",
      "portuguesePhrase": "Ele não precisa vir.",
      "englishPhrase": "He does not need to come.",
      "direction": "en-pt",
      "level": 1,
      "lastReviewed": null,
      "nextReview": 1706140900000,
      "errorCount": 0,
      "tips": "'Need' pode ser verbo comum ou modal.",
      "createdAt": 1706140900000
    }
  ]
}
